ninjalinker/__init__.py
ninjalinker/cli.py
ninjalinker/wgexpection/Devicelist.py
ninjalinker/wgexpection/__init__.py
ninjalinker/wgexpection/wireguardexpections.py
ninjalinker/wglib/__init__.py
ninjalinker/wglib/auth.py
ninjalinker/wglib/flavourfinder.py
ninjalinker/wglib/freshinstaller.py
ninjalinker/wglib/headlessdevice.py
ninjalinker/wglib/storesess.py
ninjalinker/wglib/wg.py
ninjalinker/wglib/windowswg.py
ninjalinker/wglib/wizard.py
ninjalinker-0.0.7.dist-info/METADATA
ninjalinker-0.0.7.dist-info/WHEEL
ninjalinker-0.0.7.dist-info/entry_points.txt
ninjalinker-0.0.7.dist-info/top_level.txt
ninjalinker-0.0.7.dist-info/RECORD
