Metadata-Version: 2.1
Name: ninjalinker
Version: 0.0.7
Summary: NinjaLinker : A secure Python-based CLI VPN tool developed on top of WireGuard
Home-page: https://pypi.org/project/ninjalinker/
Author: Prasaanth
Author-email: prasaanth2k@gmail.com
Maintainer: Prasaanth
Requires-Dist: keyring (==23.5.0)
Requires-Dist: readchar (==4.0.5)
Requires-Dist: Requests (==2.31.0)
Requires-Dist: rich (==13.6.0)
Requires-Dist: setuptools (==68.2.2)
